{
  "updated_at_utc": "2026-03-12 19:58:41 UTC",
  "indices": {
    "spx": {
      "Symbol": "^SPX",
      "Date": "2026-03-12",
      "Time": "20:58:35",
      "Open": "6722.46",
      "High": "6726.11",
      "Low": "6671.11",
      "Close": "6672.03",
      "Volume": "1800968140"
    },
    "ndq": {
      "Symbol": "^NDQ",
      "Date": "2026-03-12",
      "Time": "20:58:31",
      "Open": "22514.582",
      "High": "22549.908",
      "Low": "22292.943",
      "Close": "22310.139",
      "Volume": "2906524681"
    },
    "dji": {
      "Symbol": "^DJI",
      "Date": "2026-03-12",
      "Time": "20:58:21",
      "Open": "47242.52",
      "High": "47242.52",
      "Low": "46668.89",
      "Close": "46685.82",
      "Volume": "222822300"
    }
  },
  "futures": {
    "es": {
      "Symbol": "ES.F",
      "Date": "2026-03-12",
      "Time": "20:48:38",
      "Open": "6741.25",
      "High": "6760.25",
      "Low": "6682",
      "Close": "6682",
      "Volume": ""
    },
    "nq": {
      "Symbol": "NQ.F",
      "Date": "2026-03-12",
      "Time": "20:48:38",
      "Open": "24843.5",
      "High": "24927",
      "Low": "24564",
      "Close": "24565.75",
      "Volume": ""
    },
    "ym": {
      "Symbol": "YM.F",
      "Date": "2026-03-12",
      "Time": "20:48:41",
      "Open": "47162",
      "High": "47251",
      "Low": "46720",
      "Close": "46777",
      "Volume": ""
    }
  },
  "fx": {
    "usdkrw": {
      "rate": 1475.661968,
      "time_last_update_utc": "Thu, 12 Mar 2026 00:02:31 +0000"
    }
  }
}