{
  "updated_at_utc": "2026-05-26 04:44:16 UTC",
  "indices": {
    "spx": {
      "Symbol": "^SPX",
      "Date": "2026-05-22",
      "Time": "23:00:00",
      "Open": "7468.8",
      "High": "7506.3",
      "Low": "7463.3",
      "Close": "7473.5",
      "Volume": "2697941253"
    },
    "ndq": {
      "Symbol": "^NDQ",
      "Date": "2026-05-22",
      "Time": "23:00:00",
      "Open": "26381.56",
      "High": "26504.55",
      "Low": "26309.8",
      "Close": "26343.97",
      "Volume": "4873373802"
    },
    "dji": {
      "Symbol": "^DJI",
      "Date": "2026-05-22",
      "Time": "23:00:00",
      "Open": "50434.7",
      "High": "50830.2",
      "Low": "50434.7",
      "Close": "50579.7",
      "Volume": "362269477"
    }
  },
  "futures": {
    "es": {
      "Symbol": "ES.F",
      "Date": "2026-05-26",
      "Time": "06:34:07",
      "Open": "7563.75",
      "High": "7565",
      "Low": "7531.75",
      "Close": "7541.25",
      "Volume": ""
    },
    "nq": {
      "Symbol": "NQ.F",
      "Date": "2026-05-26",
      "Time": "06:34:13",
      "Open": "29972.25",
      "High": "29972.25",
      "Low": "29772.75",
      "Close": "29819.25",
      "Volume": ""
    },
    "ym": {
      "Symbol": "YM.F",
      "Date": "2026-05-26",
      "Time": "06:33:59",
      "Open": "51124",
      "High": "51132",
      "Low": "50940",
      "Close": "50980",
      "Volume": ""
    }
  },
  "fx": {
    "usdkrw": {
      "rate": 1512.242841,
      "time_last_update_utc": "Tue, 26 May 2026 00:02:31 +0000"
    }
  }
}