{
  "updated_at_utc": "2026-03-31 16:07:00 UTC",
  "items": [
    {
      "title": "Volvo leans on Chinese parent Geely to survive in tough car market",
      "link": "https://www.investing.com/news/stock-market-news/volvo-cars-to-swap-300-million-of-polestar-debt-to-equity-to-consolidate-us-manufacturing-4589309",
      "summary": "",
      "title_ko": "볼보는 까다로운 자동차 시장에서 살아남기 위해 중국 모기업 지리 (Geely) 에 기대고 있다.",
      "summary_ko": ""
    },
    {
      "title": "Oracle lays off employees in latest cuts",
      "link": "https://www.investing.com/news/stock-market-news/oracle-lays-off-employees-in-latest-cuts-93CH-4591008",
      "summary": "",
      "title_ko": "오라클, 최신 인하안으로 직원 해고",
      "summary_ko": ""
    },
    {
      "title": "Warren Buffett will not commit to more donations to Gates Foundation",
      "link": "https://www.investing.com/news/stock-market-news/warren-buffett-will-not-commit-to-more-donations-to-gates-foundation-4590991",
      "summary": "",
      "title_ko": "워렌 버핏은 게이츠 재단에 더 많은 기부를 약속하지 않을 것입니다.",
      "summary_ko": ""
    },
    {
      "title": "Turkey stocks higher at close of trade; BIST 100 up 1.30%",
      "link": "https://www.investing.com/news/stock-market-news/turkey-stocks-higher-at-close-of-trade-bist-100-up-130-4590990",
      "summary": "",
      "title_ko": "터키 주식은 거래 마감 시점에서 더 높습니다. BIST 100은 1.30% 상승했습니다.",
      "summary_ko": ""
    },
    {
      "title": "US job openings fall in February; hiring lowest since pandemic",
      "link": "https://www.investing.com/news/economic-indicators/us-job-openings-fall-in-february-hiring-lowest-since-pandemic-4590931",
      "summary": "",
      "title_ko": "미국 채용 공고는 2월에 떨어지며, 팬데믹 이후 채용률이 가장 낮습니다.",
      "summary_ko": ""
    },
    {
      "title": "US consumer confidence nudges higher in March",
      "link": "https://www.investing.com/news/economic-indicators/us-consumer-confidence-nudges-higher-in-march-4590836",
      "summary": "",
      "title_ko": "3월 미국 소비자 신뢰지수 상승",
      "summary_ko": ""
    },
    {
      "title": "U.S. Job Openings Decline Slightly, Falling Short of Forecast",
      "link": "https://www.investing.com/news/economic-indicators/us-job-openings-decline-slightly-falling-short-of-forecast-93CH-4590799",
      "summary": "",
      "title_ko": "미국 구인공고는 소폭 감소, 전망치 미달",
      "summary_ko": ""
    },
    {
      "title": "Consumer confidence rises, surpassing forecasts",
      "link": "https://www.investing.com/news/economic-indicators/consumer-confidence-rises-surpassing-forecasts-93CH-4590796",
      "summary": "",
      "title_ko": "예측을 뛰어넘는 소비자 신뢰 상승",
      "summary_ko": ""
    },
    {
      "title": "USD/JPY slips as Yen gains on intervention threats and BoJ's hawkish tone",
      "link": "https://www.fxstreet.com/news/usd-jpy-slips-as-yen-gains-on-intervention-threats-and-bojs-hawkish-tone-202603311552",
      "summary": "The USD/JPY fell to near the 159.00 level, extending its slide below the 160.00 barrier on Tuesday as the Japanese Yen (JPY) finds support from intervention threats and hawkish signals from policymakers, while the US Dol",
      "title_ko": "엔화가 개입 위협과 BOJ의 매파적인 어조를 얻음에 따라 USD/JPY가 하락합니다.",
      "summary_ko": "일본 엔화 (JPY) 가 정책 입안자의 개입 위협과 매파적인 신호로부터 지원을 발견함에 따라 USD/JPY는 159.00 수준에 근접하여 화요일 160.00 장벽 아래로 슬라이드를 확장했습니다. 반면 미국 DOL"
    },
    {
      "title": "US CB Consumer Confidence Index rose to 91.8 in March",
      "link": "https://www.fxstreet.com/news/us-cb-consumer-confidence-index-rose-to-918-in-march-202603311535",
      "summary": "US consumer sentiment picked up marginal pace in March, as the Conference Board’s Consumer Confidence Index ticked a tad higher to 91.8 from February’s 91.0 (revised from 91.2).",
      "title_ko": "3월 미국 CB 소비자 신뢰 지수는 91.8로 상승했습니다.",
      "summary_ko": "컨퍼런스 보드의 소비자 신뢰 지수가 91.0 (91.2에서 수정) 에서 91.8로 떨어지면서 3월 미국 소비심리가 소폭 상승했다."
    }
  ]
}