{
  "updated_at_utc": "2026-04-20 23:09:41 UTC",
  "items": [
    {
      "title": "Snap names Doug Hott as new CFO",
      "link": "https://www.investing.com/news/stock-market-news/snap-names-doug-hott-as-new-cfo-4624946",
      "summary": "",
      "title_ko": "Snap은 Doug Hott을 새로운 CFO로 지명합니다.",
      "summary_ko": ""
    },
    {
      "title": "GM lured new product chief with pay package totaling $40 million",
      "link": "https://www.investing.com/news/stock-market-news/gm-lured-new-product-chief-with-pay-package-totaling-40-million-4624937",
      "summary": "",
      "title_ko": "GM은 총 4천만 달러의 급여 패키지로 신제품 책임자를 유인했다 ($ 40 million).",
      "summary_ko": ""
    },
    {
      "title": "Texas environmental network plans to protest SpaceX analyst meetings",
      "link": "https://www.investing.com/news/stock-market-news/texas-environmental-network-plans-to-protest-spacex-analyst-meetings-4624933",
      "summary": "",
      "title_ko": "텍사스 환경 네트워크는 SpaceX 분석가 회의에 항의할 계획입니다.",
      "summary_ko": ""
    },
    {
      "title": "Alaska Air pulls forecast as Iran-linked fuel surge hits margins",
      "link": "https://www.investing.com/news/stock-market-news/alaska-air-pulls-2026-profit-forecast-amid-fuel-costs-related-uncertainty-4624720",
      "summary": "",
      "title_ko": "알래스카 항공은 이란과 연계된 연료 서지가 마진에 도달함에 따라 예측을 당깁니다.",
      "summary_ko": ""
    },
    {
      "title": "German industry faces stagnation in 2026, BDI says",
      "link": "https://www.investing.com/news/economic-indicators/german-industry-faces-stagnation-in-2026-bdi-says-4622435",
      "summary": "",
      "title_ko": "BDI에 따르면 2026년 독일 산업은 침체에 직면하게 된다.",
      "summary_ko": ""
    },
    {
      "title": "German producer prices fall 0.2% in March, beat forecasts",
      "link": "https://www.investing.com/news/economic-indicators/german-producer-prices-fall-02-in-march-beat-forecasts-93CH-4622420",
      "summary": "",
      "title_ko": "독일 생산자 가격은 3월에 0.2% 하락, 예측을 능가",
      "summary_ko": ""
    },
    {
      "title": "German producer prices fall 0.2% y/y in March",
      "link": "https://www.investing.com/news/economic-indicators/german-producer-prices-fall-02-yy-in-march-4622375",
      "summary": "",
      "title_ko": "3월 독일 생산자 가격 전년 대비 0.2% 하락",
      "summary_ko": ""
    },
    {
      "title": "China keeps loan prime rate unchanged for 11th month in April",
      "link": "https://www.investing.com/news/economic-indicators/china-keeps-loan-prime-rate-unchanged-for-11th-month-in-april-4622290",
      "summary": "",
      "title_ko": "중국, 4월 11개월째 대출금리 변동 없음",
      "summary_ko": ""
    },
    {
      "title": "China: Energy resilience under Hormuz shock – Commerzbank",
      "link": "https://www.fxstreet.com/news/china-energy-resilience-under-hormuz-shock-commerzbank-202604202149",
      "summary": "Commerzbank’s Dr. Henry Hao argues China is better positioned than other Asian economies to withstand energy disruptions from Middle East tensions and Strait of Hormuz risks.",
      "title_ko": "중국: 호르무즈 쇼크 하의 에너지 복원력 – 코메르츠방크",
      "summary_ko": "코메르츠방크 (Commerzbank) 의 헨리 하오 (Henry Hao) 박사는 중국이 중동 긴장과 호르무즈 해협 위험으로 인한 에너지 혼란을 견딜 수 있는 다른 아시아 경제국보다 더 나은 위치에 있다고 주장한다."
    },
    {
      "title": "USD/JPY holds below 159.00 as Iran ceasefire edges toward Wednesday deadline",
      "link": "https://www.fxstreet.com/news/usd-jpy-holds-below-15900-as-iran-ceasefire-edges-toward-wednesday-deadline-202604202123",
      "summary": "USD/JPY edged lower by less than 0.1% on Monday, trading in a tight range around 158.80.",
      "title_ko": "이란이 수요일 마감일을 향해 휴전함에 따라 USD/JPY는 159.00 미만으로 유지됩니다.",
      "summary_ko": "USD/JPY는 월요일에 0.1% 미만으로 하락하여 약 158.80의 타이트한 범위에서 거래되었습니다."
    }
  ]
}